llm4pcg/__init__.py
llm4pcg/competition.py
llm4pcg/utils.py
llm4pcg/models/__init__.py
llm4pcg/models/trial_context.py
llm4pcg/models/trial_loop.py
llm4pcg-1.0.2.dist-info/LICENSE
llm4pcg-1.0.2.dist-info/METADATA
llm4pcg-1.0.2.dist-info/WHEEL
llm4pcg-1.0.2.dist-info/top_level.txt
llm4pcg-1.0.2.dist-info/RECORD
