Metadata-Version: 2.1
Name: llm4pcg
Version: 1.0.2
Summary: LLM4PCG is a python package containing required and utility functions of ChatGPT4PCG competition, but modified to support local LLMs that compatible with OpenAI API interface.
Author-email: ChatGPT4PCG Organizing Team <chatgpt4pcg@gmail.com>, Pittawat Taveekitworachai <pittawat.pete@gmail.com>
Maintainer-email: Pittawat Taveekitworachai <pittawat.pete@gmail.com>
License: MIT License
Project-URL: Homepage, https://chatgpt4pcg.github.io/
Project-URL: Bug Reports, https://github.com/Pittawat2542/llm4pcg-python/issues
Project-URL: Source, https://github.com/Pittawat2542/llm4pcg-python
Keywords: chatgpt,chatgpt4pcg,competition
Classifier: Development Status :: 5 - Production/Stable
Classifier: Intended Audience :: Developers
Classifier: Topic :: Software Development
Classifier: License :: OSI Approved :: MIT License
Classifier: Programming Language :: Python :: 3
Classifier: Programming Language :: Python :: 3.11
Classifier: Programming Language :: Python :: 3 :: Only
Requires-Python: >=3.11
License-File: LICENSE
Requires-Dist: openai
